mqtt_client/__init__.py
mqtt_client/mqtt_client.py
mqtt_client/subscribe_callbacks.py
mqtt_client-1.3.0.data/scripts/mqtt-client
mqtt_client-1.3.0.dist-info/METADATA
mqtt_client-1.3.0.dist-info/WHEEL
mqtt_client-1.3.0.dist-info/top_level.txt
mqtt_client-1.3.0.dist-info/RECORD
