Metadata-Version: 2.1
Name: mqtt-client
Version: 1.3.0
Summary: Simple MQTT Client.
Home-page: https://github.com/sdeancos/mqtt-client
Author: Samuel de Ancos
Author-email: sdeancos@gmail.com
License: UNKNOWN
Keywords: mqtt
Platform: UNKNOWN
Requires-Python: >=3.6
Requires-Dist: docopt
Requires-Dist: paho-mqtt
Requires-Dist: terminaltables
